phi/__init__.py
phi/aws/__init__.py
phi/aws/aws_operator.py
phi/backend_api/__init__.py
phi/backend_api/api_client.py
phi/backend_api/api_exceptions.py
phi/backend_api/api_utils.py
phi/backend_api/auth_api.py
phi/backend_api/workspace_api.py
phi/cli/__init__.py
phi/cli/cli_app.py
phi/cli/cli_operator.py
phi/cli/dx/__init__.py
phi/cli/dx/dx_app.py
phi/cli/gcp/__init__.py
phi/cli/gcp/gcp_app.py
phi/cli/gcp/gke/__init__.py
phi/cli/gcp/gke/gke_app.py
phi/cli/k8s/__init__.py
phi/cli/k8s/k8s_app.py
phi/cli/wf/__init__.py
phi/cli/wf/wf_app.py
phi/cli/ws/__init__.py
phi/cli/ws/ws_app.py
phi/conf/__init__.py
phi/conf/constants.py
phi/conf/phi_cli_creds.py
phi/conf/phi_conf.py
phi/conf/tbd_old_phi_conf.py
phi/databox/__init__.py
phi/databox/databox_operator.py
phi/docker/__init__.py
phi/docker/docker_operator.py
phi/enums/__init__.py
phi/enums/response_enums.py
phi/enums/user_enums.py
phi/k8s/__init__.py
phi/k8s/k8s_operator.py
phi/k8s/k8s_schemas.py
phi/k8s/tbd_k8s_operator.py
phi/k8s/tbd_k8s_ops.py
phi/k8s/tbd_k8s_utils.py
phi/k8s/tbd_phi_k8s_data.py
phi/local/__init__.py
phi/local/local_operator.py
phi/release/__init__.py
phi/release/release_enums.py
phi/release/release_schemas.py
phi/release/ws_releases.py
phi/schemas/__init__.py
phi/schemas/auth_schemas.py
phi/schemas/response_schemas.py
phi/schemas/user_schemas.py
phi/tbd_gcp/__init__.py
phi/tbd_gcp/gcp_enums.py
phi/tbd_gcp/gcp_operator.py
phi/tbd_gcp/gcp_schemas.py
phi/tbd_gcp/gcp_utils.py
phi/tbd_gcp/gcp_zones.py
phi/tbd_gcp/phi_gcp_data.py
phi/tbd_gcp/tbd_gcp_ops.py
phi/tbd_gcp/gke/__init__.py
phi/tbd_gcp/gke/gke_operator.py
phi/tbd_gcp/gke/gke_utils.py
phi/tbd_old_api/__init__.py
phi/tbd_old_api/client.py
phi/tbd_old_api/gcp.py
phi/tbd_old_api/kubectl.py
phi/types/__init__.py
phi/types/run_status.py
phi/utils/__init__.py
phi/utils/cli_auth_server.py
phi/utils/cli_console.py
phi/utils/common.py
phi/utils/dttm.py
phi/utils/enums.py
phi/utils/filesystem.py
phi/utils/git.py
phi/utils/log.py
phi/utils/pyproject.py
phicli-0.1.31.dist-info/LICENSE.txt
phicli-0.1.31.dist-info/METADATA
phicli-0.1.31.dist-info/WHEEL
phicli-0.1.31.dist-info/entry_points.txt
phicli-0.1.31.dist-info/top_level.txt
phicli-0.1.31.dist-info/RECORD
